melanoma_segmentation/__init__.py
melanoma_segmentation/configs/__init__.py
melanoma_segmentation/configs/config_setting.py
melanoma_segmentation/datasets/__init__.py
melanoma_segmentation/datasets/data.py
melanoma_segmentation/datasets/image_data.py
melanoma_segmentation/datasets/split_data.py
melanoma_segmentation/models/__init__.py
melanoma_segmentation/models/attention_unet.py
melanoma_segmentation/models/r2u_att_unet.py
melanoma_segmentation/models/residual_recurrent_unet.py
melanoma_segmentation/models/trans_unet.py
melanoma_segmentation/models/transform.py
melanoma_segmentation/models/unet.py
melanoma_segmentation/results/__init__.py
melanoma_segmentation/results/evaluator.py
melanoma_segmentation/results/plots.py
melanoma_segmentation/utils/__init__.py
melanoma_segmentation/utils/preparation_tools.py
melanoma_segmentation-1.4.0.dist-info/LICENSE
melanoma_segmentation-1.4.0.dist-info/METADATA
melanoma_segmentation-1.4.0.dist-info/WHEEL
melanoma_segmentation-1.4.0.dist-info/top_level.txt
melanoma_segmentation-1.4.0.dist-info/RECORD
