Metadata-Version: 2.1
Name: melanoma-segmentation
Version: 1.4.0
Summary: Melanoma segmentation and classification
Author: Santiago Martínez Novoa
Author-email: s.martinezn@uniandes.edu.co
License: MIT
Keywords: melanoma segmentation classification
License-File: LICENSE
Requires-Dist: torch==2.3.0
Requires-Dist: torchaudio==2.3.0
Requires-Dist: torchvision==0.18.0
Requires-Dist: albumentations
Requires-Dist: numpy
Requires-Dist: pandas
Requires-Dist: scikit-learn
Requires-Dist: kaggle
Requires-Dist: resnest
Requires-Dist: geffnet
Requires-Dist: opencv-python
Requires-Dist: pretrainedmodels
Requires-Dist: tqdm
Requires-Dist: Pillow
Requires-Dist: packaging
